f3wikidatabot/__init__.py
f3wikidatabot/bot.py
f3wikidatabot/features.py
f3wikidatabot/forge.py
f3wikidatabot/license.py
f3wikidatabot/main.py
f3wikidatabot/plugin.py
f3wikidatabot/tests/__init__.py
f3wikidatabot/tests/test_bot.py
f3wikidatabot/tests/test_features.py
f3wikidatabot/tests/test_license.py
f3wikidatabot/tests/test_plugin.py
f3wikidatabot/tests/test_util.py
f3wikidatabot/tests/wikidata.py
f3wikidatabot/util.py
f3wikidatabot-0.0.6.dist-info/LICENSE
f3wikidatabot-0.0.6.dist-info/METADATA
f3wikidatabot-0.0.6.dist-info/WHEEL
f3wikidatabot-0.0.6.dist-info/RECORD
